Metadata-Version: 1.1
Name: package-oncom
Version: 0.7
Summary: Cuma latihan upload package 1
Home-page: http://github.com/blahblah/package-oncom
Author: Yanzen
Author-email: yanzen@example.com
License: MIT
Platform: UNKNOWN
Classifier: Development Status :: 3 - Alpha
Classifier: License :: OSI Approved :: MIT License
Classifier: Programming Language :: Python :: 3
Classifier: Topic :: Text Processing :: Linguistic
